panopto_dl/__init__.py
panopto_dl/chatgpt.py
panopto_dl/download_all.py
panopto_dl/main.py
panopto_dl/PanoptoDownloader/PanoptoDownloader.py
panopto_dl/PanoptoDownloader/__init__.py
panopto_dl/PanoptoDownloader/__main__.py
panopto_dl/PanoptoDownloader/__version__.py
panopto_dl/PanoptoDownloader/exceptions.py
panopto_dl/PanoptoDownloader/hls_downloader.py
panopto_dl-0.1.1.dist-info/LICENSE
panopto_dl-0.1.1.dist-info/METADATA
panopto_dl-0.1.1.dist-info/WHEEL
panopto_dl-0.1.1.dist-info/top_level.txt
panopto_dl-0.1.1.dist-info/RECORD
