Metadata-Version: 2.1
Name: panopto_dl
Version: 0.1.1
Summary: Download video from Panopto
Home-page: https://github.com/samsonq/panopto-dl
Author: Samson Qian
Author-email: samsonqian@gmail.com
License: MIT
Keywords: panopto download video
Requires-Python: >=3.7
License-File: LICENSE
